asgi_user_agents/__about__.py
asgi_user_agents/__init__.py
asgi_user_agents/datastructures.py
asgi_user_agents/middleware.py
asgi_user_agents/py.typed
asgi_user_agents/requests.py
asgi_user_agents/types.py
asgi_user_agents-0.2.0.dist-info/METADATA
asgi_user_agents-0.2.0.dist-info/WHEEL
asgi_user_agents-0.2.0.dist-info/licenses/LICENSE
asgi_user_agents-0.2.0.dist-info/RECORD
