Metadata-Version: 2.3
Name: asgi-user-agents
Version: 0.2.0
Summary: User Agent integration for ASGI applications.
Project-URL: Documentation, https://github.com/hasansezertasan/asgi-user-agents#readme
Project-URL: Issues, https://github.com/hasansezertasan/asgi-user-agents/issues
Project-URL: Source, https://github.com/hasansezertasan/asgi-user-agents
Author-email: Hasan Sezer Taşan <hasansezertasan@gmail.com>
Maintainer-email: Hasan Sezer Taşan <hasansezertasan@gmail.com>
License-Expression: MIT
License-File: LICENSE
Keywords: asgi,fastapi,litestar,quart,starlette
Classifier: Development Status :: 3 - Alpha
Classifier: Environment :: Web Environment
Classifier: Framework :: AsyncIO
Classifier: Framework :: FastAPI
Classifier: Intended Audience :: Developers
Classifier: Intended Audience :: Information Technology
Classifier: License :: OSI Approved :: MIT License
Classifier: Operating System :: OS Independent
Classifier: Programming Language :: Python
Classifier: Programming Language :: Python :: 3
Classifier: Programming Language :: Python :: 3 :: Only
Classifier: Programming Language :: Python :: 3.8
Classifier: Programming Language :: Python :: 3.9
Classifier: Programming Language :: Python :: 3.10
Classifier: Programming Language :: Python :: 3.11
Classifier: Programming Language :: Python :: 3.12
Classifier: Programming Language :: Python :: Implementation :: CPython
Classifier: Programming Language :: Python :: Implementation :: PyPy
Classifier: Topic :: Internet
Classifier: Topic :: Internet :: WWW/HTTP
Classifier: Topic :: Internet :: WWW/HTTP :: HTTP Servers
Classifier: Topic :: Software Development
Classifier: Topic :: Software Development :: Libraries
Classifier: Topic :: Software Development :: Libraries :: Application Frameworks
Classifier: Topic :: Software Development :: Libraries :: Python Modules
Classifier: Typing :: Typed
Requires-Python: >=3.8
Requires-Dist: user-agents
